distrans/__init__.py
distrans/exceptions.py
distrans/formatting.py
distrans/main.py
distrans/snake.py
distrans/type.py
distrans-1.1.1.dist-info/METADATA
distrans-1.1.1.dist-info/WHEEL
distrans-1.1.1.dist-info/license.txt
distrans-1.1.1.dist-info/top_level.txt
distrans-1.1.1.dist-info/RECORD
