Metadata-Version: 2.1
Name: distrans
Version: 1.1.1
Summary: A simple translation library for discord bots
Home-page: https://github.com/yatochka-dev/discordBot-translation
Author: Yatochka
Author-email: philipchef13@gmail.com
Classifier: Programming Language :: Python :: 3
Classifier: License :: OSI Approved :: MIT License
Classifier: Operating System :: OS Independent
License-File: license.txt
Requires-Dist: disnake
Requires-Dist: asgiref
